raspi_lora/__init__.py
raspi_lora/constants.py
raspi_lora/lora.py
raspi_lora-0.2.dist-info/LICENSE
raspi_lora-0.2.dist-info/METADATA
raspi_lora-0.2.dist-info/WHEEL
raspi_lora-0.2.dist-info/top_level.txt
raspi_lora-0.2.dist-info/RECORD
